{"1210.mid": "Beethoven", "1211.mid": "Beethoven", "1212.mid": "Beethoven", "1213.mid": "Beethoven", "1214.mid": "Beethoven", "1215.mid": "Beethoven", "1216.mid": "Beethoven", "1217.mid": "Beethoven", "1218.mid": "Beethoven", "1219.mid": "Beethoven", "1220.mid": "Beethoven", "1221.mid": "Beethoven", "1222.mid": "Beethoven", "1223.mid": "Beethoven", "1224.mid": "Beethoven", "1225.mid": "Beethoven", "1226.mid": "Beethoven", "1227.mid": "Beethoven", "1228.mid": "Beethoven", "1229.mid": "Beethoven", "1230.mid": "Beethoven", "1231.mid": "Beethoven", "1232.mid": "Beethoven", "1233.mid": "Beethoven", "1234.mid": "Beethoven", "1235.mid": "Beethoven", "1236.mid": "Beethoven", "1237.mid": "Beethoven", "1238.mid": "Beethoven", "1239.mid": "Beethoven", "1240.mid": "Beethoven", "1241.mid": "Beethoven", "1242.mid": "Beethoven", "1243.mid": "Beethoven", "1244.mid": "Beethoven", "1245.mid": "Beethoven", "1246.mid": "Beethoven", "1247.mid": "Beethoven", "1248.mid": "Beethoven", "1249.mid": "Beethoven", "1250.mid": "Beethoven", "1251.mid": "Beethoven", "1252.mid": "Beethoven", "1253.mid": "Beethoven", "1254.mid": "Beethoven", "1255.mid": "Beethoven", "1256.mid": "Beethoven", "1257.mid": "Beethoven", "1258.mid": "Beethoven", "1259.mid": "Beethoven", "1260.mid": "Beethoven", "1261.mid": "Beethoven", "1262.mid": "Beethoven", "1263.mid": "Beethoven", "1264.mid": "Beethoven", "1265.mid": "Beethoven", "1266.mid": "Beethoven", "1267.mid": "Beethoven", "1268.mid": "Beethoven", "1269.mid": "Beethoven", "1270.mid": "Beethoven", "1271.mid": "Beethoven", "1272.mid": "Beethoven", "1273.mid": "Beethoven", "1274.mid": "Beethoven", "1275.mid": "Beethoven", "1276.mid": "Beethoven", "1277.mid": "Beethoven", "1278.mid": "Beethoven", "1279.mid": "Beethoven", "1280.mid": "Beethoven", "1281.mid": "Beethoven", "1282.mid": "Beethoven", "1283.mid": "Beethoven", "1284.mid": "Beethoven", "1285.mid": "Beethoven", "1286.mid": "Beethoven", "1287.mid": "Beethoven", "1288.mid": "Beethoven", "1289.mid": "Beethoven", "1290.mid": "Beethoven", "1291.mid": "Beethoven", "1292.mid": "Beethoven", "1293.mid": "Beethoven", "1294.mid": "Beethoven", "1295.mid": "Beethoven", "1296.mid": "Beethoven", "1297.mid": "Beethoven", "1298.mid": "Beethoven", "1299.mid": "Beethoven", "1300.mid": "Beethoven", "1301.mid": "Beethoven", "1302.mid": "Beethoven", "1303.mid": "Beethoven", "1304.mid": "Beethoven", "1305.mid": "Beethoven", "1306.mid": "Beethoven", "1307.mid": "Beethoven", "1308.mid": "Beethoven", "1309.mid": "Beethoven", "1310.mid": "Beethoven", "1311.mid": "Beethoven", "1312.mid": "Beethoven", "1313.mid": "Beethoven", "1314.mid": "Beethoven", "1315.mid": "Beethoven", "1316.mid": "Beethoven", "1317.mid": "Beethoven", "1318.mid": "Beethoven", "1319.mid": "Beethoven", "1320.mid": "Beethoven", "1321.mid": "Beethoven", "1322.mid": "Beethoven", "1323.mid": "Beethoven", "1324.mid": "Beethoven", "1325.mid": "Beethoven", "1326.mid": "Beethoven", "1327.mid": "Beethoven", "1328.mid": "Beethoven", "1329.mid": "Beethoven", "1330.mid": "Beethoven", "1331.mid": "Beethoven", "1332.mid": "Beethoven", "1333.mid": "Beethoven", "1334.mid": "Beethoven", "1335.mid": "Beethoven", "1336.mid": "Beethoven", "1337.mid": "Beethoven", "1338.mid": "Beethoven", "1339.mid": "Beethoven", "1340.mid": "Beethoven", "1341.mid": "Beethoven", "1342.mid": "Beethoven", "1343.mid": "Beethoven", "1344.mid": "Beethoven", "1345.mid": "Beethoven", "1346.mid": "Beethoven", "1347.mid": "Beethoven", "1348.mid": "Beethoven", "1349.mid": "Beethoven", "1350.mid": "Beethoven", "1351.mid": "Beethoven", "1352.mid": "Beethoven", "1353.mid": "Beethoven", "1354.mid": "Beethoven", "1355.mid": "Beethoven", "1356.mid": "Beethoven", "1357.mid": "Beethoven", "1358.mid": "Beethoven", "1359.mid": "Beethoven", "1360.mid": "Beethoven", "1361.mid": "Beethoven", "1362.mid": "Beethoven", "1363.mid": "Beethoven", "1364.mid": "Beethoven", "1365.mid": "Beethoven", "1366.mid": "Beethoven", "1367.mid": "Beethoven", "1368.mid": "Beethoven", "1369.mid": "Beethoven", "1370.mid": "Beethoven", "1371.mid": "Beethoven", "1372.mid": "Beethoven", "1373.mid": "Beethoven", "1374.mid": "Beethoven", "1375.mid": "Beethoven", "1376.mid": "Beethoven", "1377.mid": "Beethoven", "1378.mid": "Beethoven", "1379.mid": "Beethoven", "1380.mid": "Beethoven", "1381.mid": "Beethoven", "1382.mid": "Beethoven", "1383.mid": "Beethoven", "1384.mid": "Beethoven", "1385.mid": "Beethoven", "1386.mid": "Beethoven", "1387.mid": "Beethoven", "1388.mid": "Beethoven", "1389.mid": "Beethoven", "1390.mid": "Beethoven", "1391.mid": "Beethoven", "1392.mid": "Beethoven", "1393.mid": "Beethoven", "1394.mid": "Beethoven", "1395.mid": "Beethoven", "1396.mid": "Beethoven", "1397.mid": "Beethoven", "1398.mid": "Beethoven", "1399.mid": "Beethoven", "1400.mid": "Beethoven", "1401.mid": "Beethoven", "1402.mid": "Beethoven", "1403.mid": "Beethoven", "1404.mid": "Beethoven", "1405.mid": "Beethoven", "1406.mid": "Beethoven", "1407.mid": "Beethoven", "1408.mid": "Beethoven", "1409.mid": "Beethoven", "1410.mid": "Beethoven", "1411.mid": "Beethoven", "1412.mid": "Beethoven", "1413.mid": "Beethoven", "1414.mid": "Beethoven", "1415.mid": "Beethoven", "1416.mid": "Beethoven", "1417.mid": "Beethoven", "1418.mid": "Beethoven", "1419.mid": "Beethoven", "1420.mid": "Beethoven", "1421.mid": "Beethoven", "1422.mid": "Beethoven", "1423.mid": "Beethoven", "1424.mid": "Beethoven", "1425.mid": "Beethoven", "1426.mid": "Beethoven", "1427.mid": "Beethoven", "1428.mid": "Beethoven", "1429.mid": "Beethoven", "1430.mid": "Beethoven", "1431.mid": "Beethoven", "1432.mid": "Beethoven", "1433.mid": "Beethoven", "1434.mid": "Beethoven", "1435.mid": "Beethoven", "1436.mid": "Beethoven", "1437.mid": "Beethoven", "1438.mid": "Beethoven", "1439.mid": "Beethoven", "1440.mid": "Beethoven", "1441.mid": "Beethoven", "1442.mid": "Beethoven", "1443.mid": "Beethoven", "1444.mid": "Beethoven", "1445.mid": "Beethoven", "1446.mid": "Beethoven", "1447.mid": "Beethoven", "1448.mid": "Beethoven", "1449.mid": "Beethoven", "1450.mid": "Beethoven", "1451.mid": "Beethoven", "1452.mid": "Beethoven", "1453.mid": "Beethoven", "1454.mid": "Beethoven", "1455.mid": "Beethoven", "1456.mid": "Beethoven", "1457.mid": "Beethoven", "1458.mid": "Beethoven", "1459.mid": "Beethoven", "1460.mid": "Beethoven", "1461.mid": "Beethoven", "1462.mid": "Beethoven", "1463.mid": "Beethoven", "1464.mid": "Beethoven", "1465.mid": "Beethoven", "1466.mid": "Beethoven", "1467.mid": "Beethoven", "1468.mid": "Beethoven", "1469.mid": "Beethoven", "1470.mid": "Beethoven", "1471.mid": "Beethoven", "1472.mid": "Beethoven", "1473.mid": "Beethoven", "1474.mid": "Beethoven", "1475.mid": "Beethoven", "1476.mid": "Beethoven", "1477.mid": "Beethoven", "1478.mid": "Beethoven", "1479.mid": "Beethoven", "1480.mid": "Beethoven", "1481.mid": "Beethoven", "1482.mid": "Beethoven", "1483.mid": "Beethoven", "1484.mid": "Beethoven", "1485.mid": "Beethoven", "1486.mid": "Beethoven", "1487.mid": "Beethoven", "1488.mid": "Beethoven", "1489.mid": "Beethoven", "1490.mid": "Beethoven", "1491.mid": "Beethoven", "1492.mid": "Beethoven", "1493.mid": "Beethoven", "1494.mid": "Beethoven", "1495.mid": "Beethoven", "1496.mid": "Beethoven", "1497.mid": "Beethoven", "1498.mid": "Beethoven", "1499.mid": "Beethoven", "1500.mid": "Beethoven", "1501.mid": "Beethoven", "1502.mid": "Beethoven", "1503.mid": "Beethoven", "1504.mid": "Beethoven", "1505.mid": "Beethoven", "1506.mid": "Beethoven", "1507.mid": "Beethoven", "1508.mid": "Beethoven", "1509.mid": "Beethoven", "1510.mid": "Beethoven", "1511.mid": "Beethoven", "1512.mid": "Beethoven", "1513.mid": "Beethoven", "1514.mid": "Beethoven", "1515.mid": "Beethoven", "1516.mid": "Beethoven", "1517.mid": "Beethoven", "1518.mid": "Beethoven", "1519.mid": "Beethoven", "1520.mid": "Beethoven", "1521.mid": "Beethoven", "1522.mid": "Beethoven", "1523.mid": "Beethoven", "1524.mid": "Beethoven", "1525.mid": "Beethoven", "1526.mid": "Beethoven", "1527.mid": "Beethoven", "1528.mid": "Beethoven", "1529.mid": "Beethoven", "1530.mid": "Beethoven", "1531.mid": "Beethoven", "1532.mid": "Beethoven", "1533.mid": "Beethoven", "1534.mid": "Beethoven", "1535.mid": "Beethoven", "1536.mid": "Beethoven", "1537.mid": "Beethoven", "1538.mid": "Beethoven", "1539.mid": "Beethoven", "1540.mid": "Beethoven", "1541.mid": "Beethoven", "1542.mid": "Beethoven", "1543.mid": "Beethoven", "1544.mid": "Beethoven", "1545.mid": "Beethoven", "1546.mid": "Beethoven", "1547.mid": "Beethoven", "1548.mid": "Beethoven", "1549.mid": "Beethoven", "1550.mid": "Beethoven", "1551.mid": "Beethoven", "1552.mid": "Beethoven", "1553.mid": "Beethoven", "1554.mid": "Beethoven", "1555.mid": "Beethoven", "1556.mid": "Beethoven", "1557.mid": "Beethoven", "1558.mid": "Beethoven", "1559.mid": "Beethoven", "1560.mid": "Beethoven", "1561.mid": "Beethoven", "1562.mid": "Beethoven", "1563.mid": "Beethoven", "1564.mid": "Beethoven", "1565.mid": "Beethoven", "1566.mid": "Beethoven", "1567.mid": "Beethoven", "1568.mid": "Beethoven", "1569.mid": "Beethoven", "1570.mid": "Beethoven", "1571.mid": "Beethoven", "1572.mid": "Beethoven", "1573.mid": "Beethoven", "1574.mid": "Beethoven", "1575.mid": "Beethoven", "1576.mid": "Beethoven", "1577.mid": "Beethoven", "1578.mid": "Beethoven", "1579.mid": "Beethoven", "1580.mid": "Beethoven", "1581.mid": "Beethoven", "1582.mid": "Beethoven", "1583.mid": "Beethoven", "1584.mid": "Beethoven", "1585.mid": "Beethoven", "1586.mid": "Beethoven", "1587.mid": "Beethoven", "1588.mid": "Beethoven", "1589.mid": "Beethoven", "1590.mid": "Beethoven", "1591.mid": "Beethoven", "1592.mid": "Beethoven", "1593.mid": "Beethoven", "1594.mid": "Beethoven", "1595.mid": "Beethoven", "1596.mid": "Beethoven", "1597.mid": "Beethoven", "1598.mid": "Beethoven"}